innvariant/__init__.py
innvariant/networkx/__init__.py
innvariant/networkx/generators.py
innvariant/tools.py
innvariant-0.4.0.dist-info/WHEEL
innvariant-0.4.0.dist-info/METADATA
innvariant-0.4.0.dist-info/RECORD
